setup.py
break/__init__.py
lm_break1.egg-info/PKG-INFO
lm_break1.egg-info/SOURCES.txt
lm_break1.egg-info/dependency_links.txt
lm_break1.egg-info/not-zip-safe
lm_break1.egg-info/top_level.txt