Metadata-Version: 1.0
Name: lm-break1
Version: 0.1
Summary: lm-break
Home-page: UNKNOWN
Author: Lujing Cen
Author-email: lujingcen@gmail.com
License: MIT
Platform: UNKNOWN
